setup.cfg
setup.py
SQLAlchemyUtils.egg-info/PKG-INFO
SQLAlchemyUtils.egg-info/SOURCES.txt
SQLAlchemyUtils.egg-info/dependency_links.txt
SQLAlchemyUtils.egg-info/not-zip-safe
SQLAlchemyUtils.egg-info/top_level.txt
sautils/__init__.py
sautils/encoders.py
sautils/mixins.py
sautils/tests/__init__.py
sautils/tests/test_encoders.py