Metadata-Version: 1.0
Name: SQLAlchemyUtils
Version: 0.0.1
Summary: Useful utilities for working with SQLAlchemy.
Home-page: UNKNOWN
Author: Tyler Treat
Author-email: ttreat31@gmail.com
License: UNKNOWN
Platform: UNKNOWN
